basey/__init__.py
basey/lib.py
basey-0.2.0.dist-info/WHEEL
basey-0.2.0.dist-info/METADATA
basey-0.2.0.dist-info/RECORD
