Metadata-Version: 2.1
Name: basey
Version: 0.2.0
Summary: Python package for encoding/decoding base 10
Author: Dan Scott
Author-email: dscott304@gmail.com
Requires-Python: >=3.9,<4.0
Classifier: Programming Language :: Python :: 3
Classifier: Programming Language :: Python :: 3.10
Classifier: Programming Language :: Python :: 3.9
